fdk_asgi/__init__.py
fdk_asgi/app.py
fdk_asgi/cli.py
fdk_asgi/exceptions.py
fdk_asgi/py.typed
fdk_asgi/types.py
fdk_asgi/utils.py
fdk_asgi-0.7.2.dist-info/LICENSE
fdk_asgi-0.7.2.dist-info/METADATA
fdk_asgi-0.7.2.dist-info/WHEEL
fdk_asgi-0.7.2.dist-info/entry_points.txt
fdk_asgi-0.7.2.dist-info/RECORD
