Metadata-Version: 2.1
Name: fdk-asgi
Version: 0.7.2
Summary: An alternative FDK to easily run any ASGI application on OCI Functions behind an API Gateway.
Home-page: https://github.com/bjoern-reetz/fdk-asgi/
License: MIT
Keywords: oci,functions,fnproject,runtime,asgi
Author: Björn Reetz
Author-email: git@bjoern-reetz.de
Requires-Python: >=3.8
Classifier: Development Status :: 4 - Beta
Classifier: Intended Audience :: Developers
Classifier: License :: OSI Approved :: MIT License
Classifier: Operating System :: OS Independent
Classifier: Programming Language :: Python :: 3
Classifier: Programming Language :: Python :: 3.8
Classifier: Programming Language :: Python :: 3.9
Classifier: Programming Language :: Python :: 3.10
Classifier: Programming Language :: Python :: 3.11
Classifier: Programming Language :: Python :: 3.12
Classifier: Topic :: Software Development :: Libraries :: Python Modules
Classifier: Typing :: Typed
Provides-Extra: cli
Requires-Dist: httptools (>=0.6.0,<0.7.0)
Requires-Dist: strenum (>=0.4.15,<0.5.0)
Requires-Dist: typer (>=0.9.0,<0.10.0) ; extra == "cli"
Requires-Dist: typing-extensions (>=4.12.0,<5.0.0) ; python_version < "3.9"
Requires-Dist: uvicorn (>=0.25,<0.26) ; extra == "cli"
Project-URL: Documentation, https://github.com/bjoern-reetz/fdk-asgi/
Project-URL: Repository, https://github.com/bjoern-reetz/fdk-asgi/
